Metadata-Version: 1.0
Name: dspkg-prob
Version: 1.2
Summary: Gaussian and Binomial Distributions
Home-page: UNKNOWN
Author: Kaustubh Mishra(chromerai)
Author-email: kaustubhmishra983@gmail.com
License: UNKNOWN
Platform: UNKNOWN
